pycrm/agents/sb3/ddpg/__init__.py
pycrm/agents/sb3/ddpg/cddpg.py
pycrm/agents/sb3/dqn/__init__.py
pycrm/agents/sb3/dqn/cdqn.py
pycrm/agents/sb3/sac/__init__.py
pycrm/agents/sb3/sac/csac.py
pycrm/agents/sb3/td3/__init__.py
pycrm/agents/sb3/td3/ctd3.py
pycrm/agents/sb3/wrapper/__init__.py
pycrm/agents/sb3/wrapper/subproc.py
pycrm/agents/tabular/__init__.py
pycrm/agents/tabular/cql.py
pycrm/agents/tabular/ql.py
pycrm/automaton/__init__.py
pycrm/automaton/compiler.py
pycrm/automaton/machine.py
pycrm/crossproduct/__init__.py
pycrm/crossproduct/crossproduct.py
pycrm/label/__init__.py
pycrm/label/function.py
pyrewardmachines-1.0.0.dist-info/METADATA
pyrewardmachines-1.0.0.dist-info/WHEEL
pyrewardmachines-1.0.0.dist-info/licenses/LICENSE
pyrewardmachines-1.0.0.dist-info/RECORD
