Metadata-Version: 2.4
Name: pyrewardmachines
Version: 1.0.0
Summary: Python package for RL with Reward Machines and Counting Reward Machines.
Author-email: Tristan Bester <tristanbester@email.com>
License-File: LICENSE
Requires-Python: <3.13,>=3.10
Requires-Dist: gymnasium==0.29.1
Requires-Dist: numpy==1.26.4
Requires-Dist: stable-baselines3>=2.3.2
Requires-Dist: torch==2.6.0
Requires-Dist: tqdm>=4.67.1
